{"cameraMode":{"drawMode":0,"name":"Shaded","section":"Shading Mode"},"sceneLighting":false,"audioPlay":false,"sceneViewState":{"m_AlwaysRefresh":false,"showFog":true,"showSkybox":false,"showFlares":true,"showImageEffects":true,"showParticleSystems":true,"showVisualEffectGraphs":true,"m_FxEnabled":true},"in2DMode":false,"pivot":{"x":-0.011315662413835526,"y":1.2774930000305176,"z":0.15699227154254914},"rotation":{"x":0.08125797659158707,"y":0.9156571626663208,"z":-0.3170924186706543,"w":0.23401165008544923},"size":0.00001732736564008519,"orthographic":false}